quickfilereader/__init__.py
quickfilereader-0.1.0.dist-info/LICENSE
quickfilereader-0.1.0.dist-info/METADATA
quickfilereader-0.1.0.dist-info/WHEEL
quickfilereader-0.1.0.dist-info/top_level.txt
quickfilereader-0.1.0.dist-info/RECORD
